setup.py
campaign_monitor_api/__init__.py
campaign_monitor_api/campaign_monitor_api.py
campaign_monitor_api/campaign_monitor_api_tests.py
campaign_monitor_api/runtests.py
campaign_monitor_api.egg-info/PKG-INFO
campaign_monitor_api.egg-info/SOURCES.txt
campaign_monitor_api.egg-info/dependency_links.txt
campaign_monitor_api.egg-info/top_level.txt