Metadata-Version: 1.0
Name: campaign-monitor-api
Version: 2.1
Summary: A Python class that is an implementation of common Campaign Monitor API methods.
Home-page: UNKNOWN
Author: Whads/Accent SL
Author-email: whads@whads.com
License: LGPL
Keywords: campaign monitor api
Platform: UNKNOWN
Classifier: Development Status :: 3 - Alpha
Classifier: Environment :: Web Environment
Classifier: License :: OSI Approved :: GNU Library or Lesser General Public License (LGPL)
Classifier: Intended Audience :: Developers
Classifier: Operating System :: OS Independent
Classifier: Programming Language :: Python :: 2
Classifier: Topic :: Communications :: Email
